WSService/__init__.py
WSService/__main__.py
WSService/const.py
WSService/message_from_user_to_workstation.py
WSService/on_startup.py
WSService/service.py
pih_ws-1.29.dist-info/METADATA
pih_ws-1.29.dist-info/WHEEL
pih_ws-1.29.dist-info/entry_points.txt
pih_ws-1.29.dist-info/top_level.txt
pih_ws-1.29.dist-info/RECORD
