Metadata-Version: 2.1
Name: pih-ws
Version: 1.29
Summary: PIH Workstation service package
Home-page: https://pacifichosp.com/
Author: Nikita Karachentsev
Author-email: it@pacifichosp.com
License: MIT
Requires-Dist: ipih
